poet/plug/plug.py
poet/plug/poet.py
poetry_poet-0.1.12.dist-info/METADATA
poetry_poet-0.1.12.dist-info/WHEEL
poetry_poet-0.1.12.dist-info/entry_points.txt
poetry_poet-0.1.12.dist-info/RECORD
