Metadata-Version: 2.1
Name: poetry-poet
Version: 0.1.12
Summary: Poetic tooling for Poetry.
Home-page: https://github.com/sitbon/poet
Author: Phillip Sitbon
Author-email: phillip.sitbon@gmail.com
Requires-Python: >=3.8,<4.0
Classifier: Programming Language :: Python :: 3
Classifier: Programming Language :: Python :: 3.8
Classifier: Programming Language :: Python :: 3.9
Classifier: Programming Language :: Python :: 3.10
Classifier: Programming Language :: Python :: 3.11
Provides-Extra: dev
Provides-Extra: plugin
Project-URL: Repository, https://github.com/sitbon/poet
